CHANGELOG
LICENSE
MANIFEST.in
README.md
pytest.ini
setup.cfg
setup.py
tox.ini
TracMovieMacro.egg-info/PKG-INFO
TracMovieMacro.egg-info/SOURCES.txt
TracMovieMacro.egg-info/dependency_links.txt
TracMovieMacro.egg-info/entry_points.txt
TracMovieMacro.egg-info/requires.txt
TracMovieMacro.egg-info/top_level.txt
movie/__init__.py
movie/macro.py
movie/model.py
movie/utils.py
movie/video_sites.py
movie/web_ui.py
movie/htdocs/img/black.jpg
movie/htdocs/js/flowplayer.js
movie/htdocs/js/flowplayer.min.js
movie/htdocs/js/skin/all-skins.css
movie/htdocs/js/skin/functional.css
movie/htdocs/js/skin/minimalist.css
movie/htdocs/js/skin/playful.css
movie/htdocs/js/skin/img/black.png
movie/htdocs/js/skin/img/black@x2.png
movie/htdocs/js/skin/img/black_rtl.png
movie/htdocs/js/skin/img/black_rtl@x2.png
movie/htdocs/js/skin/img/flowplayer.png
movie/htdocs/js/skin/img/flowplayer@2x.png
movie/htdocs/js/skin/img/play_black.png
movie/htdocs/js/skin/img/play_black@x2.png
movie/htdocs/js/skin/img/play_black_rtl.png
movie/htdocs/js/skin/img/play_black_rtl@x2.png
movie/htdocs/js/skin/img/play_white.png
movie/htdocs/js/skin/img/play_white@x2.png
movie/htdocs/js/skin/img/play_white_rtl.png
movie/htdocs/js/skin/img/play_white_rtl@x2.png
movie/htdocs/js/skin/img/playful_black.png
movie/htdocs/js/skin/img/playful_black@x2.png
movie/htdocs/js/skin/img/playful_black_rtl.png
movie/htdocs/js/skin/img/playful_black_rtl@x2.png
movie/htdocs/js/skin/img/playful_white.png
movie/htdocs/js/skin/img/playful_white@x2.png
movie/htdocs/js/skin/img/playful_white_rtl.png
movie/htdocs/js/skin/img/playful_white_rtl@x2.png
movie/htdocs/js/skin/img/white.png
movie/htdocs/js/skin/img/white@x2.png
movie/htdocs/js/skin/img/white_rtl.png
movie/htdocs/js/skin/img/white_rtl@x2.png
movie/htdocs/swf/flowplayer.swf
tests/conftest.py
tests/test_macro.py
tests/test_utils.py
tests/test_video_sites.py