Metadata-Version: 1.1
Name: TracMovieMacro
Version: 0.3
Summary: Safely embed various movies into wiki pages
Home-page: http://trac-hacks.org/wiki/MovieMacro/
Author: Tetsuya Morimoto
Author-email: tetsuya dot morimoto at gmail dot com
License: Apache License 2.0
Keywords: trac plugin movie video html5 macro
Platform: unix
Platform: linux
Platform: osx
Platform: cygwin
Platform: win32
Classifier: Framework :: Trac
Classifier: Development Status :: 4 - Beta
Classifier: Environment :: Web Environment
Classifier: License :: OSI Approved :: Apache Software License
Classifier: Intended Audience :: Developers
Classifier: Operating System :: OS Independent
Classifier: Programming Language :: Python
Classifier: Topic :: Software Development
